parse_bank_statements/__init__.py
parse_bank_statements/banks.py
parse_bank_statements/dates.py
parse_bank_statements/pbs_gui.py
parse_bank_statements/pbs_style.py
parse_bank_statements/pdf2csv.py
parse_bank_statements-0.1.9.dist-info/LICENSE
parse_bank_statements-0.1.9.dist-info/METADATA
parse_bank_statements-0.1.9.dist-info/WHEEL
parse_bank_statements-0.1.9.dist-info/top_level.txt
parse_bank_statements-0.1.9.dist-info/RECORD
