Metadata-Version: 2.2
Name: parse_bank_statements
Version: 0.1.9
Summary: Package to parse bank statements
Home-page: https://github.com/tardini/parse_bank_statements.git
Author: Giovanni Tardini
Author-email: giovannitardini@yahoo.de
Classifier: Programming Language :: Python :: 3
Classifier: License :: OSI Approved :: MIT License
Classifier: Operating System :: OS Independent
Requires-Python: >=2.6
License-File: LICENSE
Requires-Dist: tabula_py
